longestrunsubsequence/__init__.py
longestrunsubsequence/algorithms.py
longestrunsubsequence/lrs.py
longestrunsubsequence/reduction.py
longestrunsubsequence/util.py
longestrunsubsequence-1.0.1.dist-info/LICENSE
longestrunsubsequence-1.0.1.dist-info/METADATA
longestrunsubsequence-1.0.1.dist-info/WHEEL
longestrunsubsequence-1.0.1.dist-info/top_level.txt
longestrunsubsequence-1.0.1.dist-info/RECORD
