Metadata-Version: 2.1
Name: longestrunsubsequence
Version: 1.0.1
Summary: Algorithm to compute the longest run subsequence of a string
Home-page: https://github.com/AlBi-HHU/longest-run-subsequence
Author: Sven Schrinner, Manish Goel, Michael Wulfert, Philipp Spohr, Korbinian Schneeberger, Gunnar W. Klau
Author-email: albi@hhu.de
License: MIT License
Platform: UNKNOWN
Classifier: Programming Language :: Python :: 3
Classifier: License :: OSI Approved :: MIT License
Classifier: Operating System :: OS Independent
Classifier: Topic :: Scientific/Engineering :: Bio-Informatics
Requires-Python: >=3.5
Provides-Extra: ilp-acceleration
Requires-Dist: PuLP (>=1.6.8) ; extra == 'ilp-acceleration'
